chaintool/__init__.py
chaintool/__main__.py
chaintool/cli.py
chaintool/command.py
chaintool/command_impl_core.py
chaintool/command_impl_op.py
chaintool/command_impl_print.py
chaintool/completions.py
chaintool/completions_setup.py
chaintool/info.py
chaintool/locks.py
chaintool/sequence.py
chaintool/sequence_impl.py
chaintool/shared.py
chaintool/shortcuts.py
chaintool/shortcuts_setup.py
chaintool/virtual_tools.py
chaintool/xfer.py
chaintool-0.2.0.dist-info/LICENSE
chaintool-0.2.0.dist-info/METADATA
chaintool-0.2.0.dist-info/WHEEL
chaintool-0.2.0.dist-info/entry_points.txt
chaintool-0.2.0.dist-info/top_level.txt
chaintool-0.2.0.dist-info/zip-safe
chaintool-0.2.0.dist-info/RECORD
