Metadata-Version: 2.1
Name: chaintool
Version: 0.2.0
Summary: a tool to chain tools into toolchains
Home-page: https://github.com/neogeographica/chaintool
Author: Joel Baxter
Author-email: joel.baxter@neogeographica.com
License: GPLv3
Platform: any
Classifier: Development Status :: 2 - Pre-Alpha
Classifier: Environment :: Console
Classifier: Intended Audience :: Developers
Classifier: License :: OSI Approved :: GNU General Public License v3 (GPLv3)
Classifier: Natural Language :: English
Classifier: Operating System :: OS Independent
Classifier: Programming Language :: Python
Classifier: Programming Language :: Python :: 3
Classifier: Programming Language :: Python :: 3 :: Only
Classifier: Programming Language :: Python :: 3.7
Classifier: Programming Language :: Python :: 3.8
Classifier: Programming Language :: Python :: 3.9
Classifier: Programming Language :: Python :: Implementation :: CPython
Classifier: Programming Language :: Python :: Implementation :: PyPy
Classifier: Topic :: Utilities
Requires-Python: >=3.7
Requires-Dist: appdirs (>=1.4.4)
Requires-Dist: colorama (>=0.4.4)
Requires-Dist: filelock (>=3.0.12)
Requires-Dist: psutil (>=5.8.0)
Requires-Dist: PyYAML (>=5.4.1)
